michaelPanUtilsLib/__init__.py
michaelPanUtilsLib/draw_colorbar_fun.py
michaelPanUtilsLib/get_submap.py
michaelPanUtilsLib/utils.py
michaelPanUtilsLib-0.0.6.dist-info/LICENSE
michaelPanUtilsLib-0.0.6.dist-info/METADATA
michaelPanUtilsLib-0.0.6.dist-info/WHEEL
michaelPanUtilsLib-0.0.6.dist-info/top_level.txt
michaelPanUtilsLib-0.0.6.dist-info/RECORD
