Metadata-Version: 2.1
Name: michaelPanUtilsLib
Version: 0.0.6
Summary: Commonly Used Functions.
Author: chuntong pan
Author-email: panzhang1314@gmail.com
Platform: all
Classifier: Programming Language :: Python :: 3
Classifier: Operating System :: OS Independent
Requires-Python: >=3.8
License-File: LICENSE
Requires-Dist: pillow
Requires-Dist: michaelPanPrintLib
Requires-Dist: numpy
Requires-Dist: pydantic
Requires-Dist: gdal
Requires-Dist: h5py
Requires-Dist: beautifulsoup4
Requires-Dist: matplotlib
Requires-Dist: requests
